setup.py
test.py
slacky/__init__.py
slacky.egg-info/PKG-INFO
slacky.egg-info/SOURCES.txt
slacky.egg-info/dependency_links.txt
slacky.egg-info/requires.txt
slacky.egg-info/top_level.txt
slacky/events/__init__.py
slacky/events/events.py
slacky/requests/__init__.py
slacky/requests/requests.py
slacky/rest/__init__.py
slacky/rest/rest.py
tests/__init__.py
tests/test_common.py
tests/api/__init__.py
tests/api/test_api.py
tests/auth/__init__.py
tests/auth/test_auth.py
tests/channels/__init__.py
tests/channels/test_channels.py