Metadata-Version: 1.1
Name: slacky
Version: 0.1.42
Summary: Package for Slack's API
Home-page: https://github.com/nabetama/slacky
Author: Mao Nabeta
Author-email: mao.nabeta@gmail.com
License: UNKNOWN
Keywords: slack
Platform: UNKNOWN
Classifier: Development Status :: 3 - Alpha
Classifier: Intended Audience :: Developers
Classifier: License :: OSI Approved :: MIT License
Classifier: Operating System :: OS Independent
Classifier: Programming Language :: Python
Classifier: Programming Language :: Python :: 2
Classifier: Programming Language :: Python :: 3
Classifier: Topic :: Communications :: Chat
Classifier: Topic :: Software Development :: Libraries
Classifier: Topic :: Software Development :: Libraries :: Python Modules
Provides: slack
